[
	{
		"name": "dazz_spawn_01",
		"fullname": "dazzle_dazz_spawn_01",
		"mp3": "/sounds/vo/dazzle/dazz_spawn_01.mp3",
		"hero_id": 50,
		"voice_id": 50,
		"text": "Dazzle!",
		"text_simple": " dazzle ",
		"criteria": "Spawn Isdazzle|Custom Isdazzle IsDazzleLoadoutSpawn",
		"pretty_criteria": "Spawning|Spawning in the loadout"
	},
	{
		"name": "dazz_spawn_02",
		"fullname": "dazzle_dazz_spawn_02",
		"mp3": "/sounds/vo/dazzle/dazz_spawn_02.mp3",
		"hero_id": 50,
		"voice_id": 50,
		"text": "Shadow Priest!",
		"text_simple": " shadow priest ",
		"criteria": "Spawn Isdazzle|Custom Isdazzle IsDazzleLoadoutSpawn",
		"pretty_criteria": "Spawning|Spawning in the loadout"
	},
	{
		"name": "dazz_spawn_03",
		"fullname": "dazzle_dazz_spawn_03",
		"mp3": "/sounds/vo/dazzle/dazz_spawn_03.mp3",
		"hero_id": 50,
		"voice_id": 50,
		"text": "I cast a long shadow.",
		"text_simple": " i cast a long shadow ",
		"criteria": "Spawn Isdazzle|Custom Isdazzle IsDazzleLoadoutSpawn",
		"pretty_criteria": "Spawning|Spawning in the loadout"
	},
	{
		"name": "dazz_spawn_04",
		"fullname": "dazzle_dazz_spawn_04",
		"mp3": "/sounds/vo/dazzle/dazz_spawn_04.mp3",
		"hero_id": 50,
		"voice_id": 50,
		"text": "The enemy pales when they see the face of Dazzle!",
		"text_simple": " the enemy pales when they see the face of dazzle ",
		"criteria": "Spawn Isdazzle|Custom Isdazzle IsDazzleLoadoutSpawn",
		"pretty_criteria": "Spawning|Spawning in the loadout"
	},
	{
		"name": "dazz_spawn_05",
		"fullname": "dazzle_dazz_spawn_05",
		"mp3": "/sounds/vo/dazzle/dazz_spawn_05.mp3",
		"hero_id": 50,
		"voice_id": 50,
		"text": "Take a care when my shadow falls upon the foe.",
		"text_simple": " take a care when my shadow falls upon the foe ",
		"criteria": "Spawn Isdazzle|Custom Isdazzle IsDazzleLoadoutSpawn",
		"pretty_criteria": "Spawning|Spawning in the loadout"
	},
	{
		"name": "dazz_battlebegins_01",
		"fullname": "dazzle_dazz_battlebegins_01",
		"mp3": "/sounds/vo/dazzle/dazz_battlebegins_01.mp3",
		"hero_id": 50,
		"voice_id": 50,
		"text": "My shadow leaps ahead!",
		"text_simple": " my shadow leaps ahead ",
		"criteria": "Custom Isdazzle IsGameStart",
		"pretty_criteria": "As the game starts"
	},
	{
		"name": "dazz_firstblood_01",
		"fullname": "dazzle_dazz_firstblood_01",
		"mp3": "/sounds/vo/dazzle/dazz_firstblood_01.mp3",
		"hero_id": 50,
		"voice_id": 50,
		"text": "First Blood! Ha ha ha ha!",
		"text_simple": " first blood ha ha ha ha ",
		"criteria": "Kill Isdazzle IsFirstBlood",
		"pretty_criteria": "Killing a hero (First Blood)"
	},
	{
		"name": "dazz_move_01",
		"fullname": "dazzle_dazz_move_01",
		"mp3": "/sounds/vo/dazzle/dazz_move_01.mp3",
		"hero_id": 50,
		"voice_id": 50,
		"text": "Yes!",
		"text_simple": " yes ",
		"criteria": "Move Isdazzle",
		"pretty_criteria": "Moving"
	},
	{
		"name": "dazz_move_02",
		"fullname": "dazzle_dazz_move_02",
		"mp3": "/sounds/vo/dazzle/dazz_move_02.mp3",
		"hero_id": 50,
		"voice_id": 50,
		"text": "Mm hm!",
		"text_simple": " mm hm ",
		"criteria": "Move Isdazzle",
		"pretty_criteria": "Moving"
	},
	{
		"name": "dazz_move_03",
		"fullname": "dazzle_dazz_move_03",
		"mp3": "/sounds/vo/dazzle/dazz_move_03.mp3",
		"hero_id": 50,
		"voice_id": 50,
		"text": "Ha ha ha ha!",
		"text_simple": " ha ha ha ha ",
		"criteria": "Move Isdazzle",
		"pretty_criteria": "Moving"
	},
	{
		"name": "dazz_move_04",
		"fullname": "dazzle_dazz_move_04",
		"mp3": "/sounds/vo/dazzle/dazz_move_04.mp3",
		"hero_id": 50,
		"voice_id": 50,
		"text": "Travel on.",
		"text_simple": " travel on ",
		"criteria": "Move Isdazzle",
		"pretty_criteria": "Moving"
	},
	{
		"name": "dazz_move_05",
		"fullname": "dazzle_dazz_move_05",
		"mp3": "/sounds/vo/dazzle/dazz_move_05.mp3",
		"hero_id": 50,
		"voice_id": 50,
		"text": "A spiritual journey.",
		"text_simple": " a spiritual journey ",
		"criteria": "Move Isdazzle",
		"pretty_criteria": "Moving"
	},
	{
		"name": "dazz_move_06",
		"fullname": "dazzle_dazz_move_06",
		"mp3": "/sounds/vo/dazzle/dazz_move_06.mp3",
		"hero_id": 50,
		"voice_id": 50,
		"text": "Confirmed.",
		"text_simple": " confirmed ",
		"criteria": "Move Isdazzle",
		"pretty_criteria": "Moving"
	},
	{
		"name": "dazz_move_07",
		"fullname": "dazzle_dazz_move_07",
		"mp3": "/sounds/vo/dazzle/dazz_move_07.mp3",
		"hero_id": 50,
		"voice_id": 50,
		"text": "Rite of passage.",
		"text_simple": " rite of passage ",
		"criteria": "Move Isdazzle",
		"pretty_criteria": "Moving"
	},
	{
		"name": "dazz_move_08",
		"fullname": "dazzle_dazz_move_08",
		"mp3": "/sounds/vo/dazzle/dazz_move_08.mp3",
		"hero_id": 50,
		"voice_id": 50,
		"text": "Of course.",
		"text_simple": " of course ",
		"criteria": "Move Isdazzle",
		"pretty_criteria": "Moving"
	},
	{
		"name": "dazz_move_09",
		"fullname": "dazzle_dazz_move_09",
		"mp3": "/sounds/vo/dazzle/dazz_move_09.mp3",
		"hero_id": 50,
		"voice_id": 50,
		"text": "From shadow to shadow.",
		"text_simple": " from shadow to shadow ",
		"criteria": "Custom Isdazzle IsDazzleLoadoutSpawn|Move Isdazzle",
		"pretty_criteria": "Spawning in the loadout|Moving"
	},
	{
		"name": "dazz_move_10",
		"fullname": "dazzle_dazz_move_10",
		"mp3": "/sounds/vo/dazzle/dazz_move_10.mp3",
		"hero_id": 50,
		"voice_id": 50,
		"text": "Indeed.",
		"text_simple": " indeed ",
		"criteria": "Move Isdazzle",
		"pretty_criteria": "Moving"
	},
	{
		"name": "dazz_move_11",
		"fullname": "dazzle_dazz_move_11",
		"mp3": "/sounds/vo/dazzle/dazz_move_11.mp3",
		"hero_id": 50,
		"voice_id": 50,
		"text": "I go where I'm needed.",
		"text_simple": " i go where im needed ",
		"criteria": "Move Isdazzle",
		"pretty_criteria": "Moving"
	},
	{
		"name": "dazz_move_12",
		"fullname": "dazzle_dazz_move_12",
		"mp3": "/sounds/vo/dazzle/dazz_move_12.mp3",
		"hero_id": 50,
		"voice_id": 50,
		"text": "On my way.",
		"text_simple": " on my way ",
		"criteria": "Move Isdazzle",
		"pretty_criteria": "Moving"
	},
	{
		"name": "dazz_move_13",
		"fullname": "dazzle_dazz_move_13",
		"mp3": "/sounds/vo/dazzle/dazz_move_13.mp3",
		"hero_id": 50,
		"voice_id": 50,
		"text": "Wait for me!",
		"text_simple": " wait for me ",
		"criteria": "Move Isdazzle",
		"pretty_criteria": "Moving"
	},
	{
		"name": "dazz_move_14",
		"fullname": "dazzle_dazz_move_14",
		"mp3": "/sounds/vo/dazzle/dazz_move_14.mp3",
		"hero_id": 50,
		"voice_id": 50,
		"text": "I'm with you.",
		"text_simple": " im with you ",
		"criteria": "Move Isdazzle",
		"pretty_criteria": "Moving"
	},
	{
		"name": "dazz_move_15",
		"fullname": "dazzle_dazz_move_15",
		"mp3": "/sounds/vo/dazzle/dazz_move_15.mp3",
		"hero_id": 50,
		"voice_id": 50,
		"text": "Healing here.",
		"text_simple": " healing here ",
		"criteria": "Move Isdazzle",
		"pretty_criteria": "Moving"
	},
	{
		"name": "dazz_move_16",
		"fullname": "dazzle_dazz_move_16",
		"mp3": "/sounds/vo/dazzle/dazz_move_16.mp3",
		"hero_id": 50,
		"voice_id": 50,
		"text": "Shadows come.",
		"text_simple": " shadows come ",
		"criteria": "Move Isdazzle",
		"pretty_criteria": "Moving"
	},
	{
		"name": "dazz_move_17",
		"fullname": "dazzle_dazz_move_17",
		"mp3": "/sounds/vo/dazzle/dazz_move_17.mp3",
		"hero_id": 50,
		"voice_id": 50,
		"text": "Who needs healing!",
		"text_simple": " who needs healing ",
		"criteria": "Custom Isdazzle IsDazzleLoadoutSpawn|Move Isdazzle",
		"pretty_criteria": "Spawning in the loadout|Moving"
	},
	{
		"name": "dazz_attack_01",
		"fullname": "dazzle_dazz_attack_01",
		"mp3": "/sounds/vo/dazzle/dazz_attack_01.mp3",
		"hero_id": 50,
		"voice_id": 50,
		"text": "Attack!",
		"text_simple": " attack ",
		"criteria": "Attack Isdazzle",
		"pretty_criteria": "Attacking"
	},
	{
		"name": "dazz_attack_02",
		"fullname": "dazzle_dazz_attack_02",
		"mp3": "/sounds/vo/dazzle/dazz_attack_02.mp3",
		"hero_id": 50,
		"voice_id": 50,
		"text": "Come, comrades!",
		"text_simple": " come comrades ",
		"criteria": "Attack Isdazzle",
		"pretty_criteria": "Attacking"
	},
	{
		"name": "dazz_attack_03",
		"fullname": "dazzle_dazz_attack_03",
		"mp3": "/sounds/vo/dazzle/dazz_attack_03.mp3",
		"hero_id": 50,
		"voice_id": 50,
		"text": "Strikedown!",
		"text_simple": " strikedown ",
		"criteria": "Attack Isdazzle",
		"pretty_criteria": "Attacking"
	},
	{
		"name": "dazz_attack_04",
		"fullname": "dazzle_dazz_attack_04",
		"mp3": "/sounds/vo/dazzle/dazz_attack_04.mp3",
		"hero_id": 50,
		"voice_id": 50,
		"text": "We fight!",
		"text_simple": " we fight ",
		"criteria": "Attack Isdazzle",
		"pretty_criteria": "Attacking"
	},
	{
		"name": "dazz_attack_05",
		"fullname": "dazzle_dazz_attack_05",
		"mp3": "/sounds/vo/dazzle/dazz_attack_05.mp3",
		"hero_id": 50,
		"voice_id": 50,
		"text": "For the shadows!",
		"text_simple": " for the shadows ",
		"criteria": "Attack Isdazzle",
		"pretty_criteria": "Attacking"
	},
	{
		"name": "dazz_attack_06",
		"fullname": "dazzle_dazz_attack_06",
		"mp3": "/sounds/vo/dazzle/dazz_attack_06.mp3",
		"hero_id": 50,
		"voice_id": 50,
		"text": "Heal or harm!",
		"text_simple": " heal or harm ",
		"criteria": "Attack Isdazzle",
		"pretty_criteria": "Attacking"
	},
	{
		"name": "dazz_attack_07",
		"fullname": "dazzle_dazz_attack_07",
		"mp3": "/sounds/vo/dazzle/dazz_attack_07.mp3",
		"hero_id": 50,
		"voice_id": 50,
		"text": "Stave them off!",
		"text_simple": " stave them off ",
		"criteria": "Attack Isdazzle",
		"pretty_criteria": "Attacking"
	},
	{
		"name": "dazz_attack_08",
		"fullname": "dazzle_dazz_attack_08",
		"mp3": "/sounds/vo/dazzle/dazz_attack_08.mp3",
		"hero_id": 50,
		"voice_id": 50,
		"text": "Dazzle them!",
		"text_simple": " dazzle them ",
		"criteria": "Attack Isdazzle",
		"pretty_criteria": "Attacking"
	},
	{
		"name": "dazz_attack_09",
		"fullname": "dazzle_dazz_attack_09",
		"mp3": "/sounds/vo/dazzle/dazz_attack_09.mp3",
		"hero_id": 50,
		"voice_id": 50,
		"text": "Bringing the pain!",
		"text_simple": " bringing the pain ",
		"criteria": "Attack Isdazzle",
		"pretty_criteria": "Attacking"
	},
	{
		"name": "dazz_attack_10",
		"fullname": "dazzle_dazz_attack_10",
		"mp3": "/sounds/vo/dazzle/dazz_attack_10.mp3",
		"hero_id": 50,
		"voice_id": 50,
		"text": "Priest of pain!",
		"text_simple": " priest of pain ",
		"criteria": "Attack Isdazzle",
		"pretty_criteria": "Attacking"
	},
	{
		"name": "dazz_attack_11",
		"fullname": "dazzle_dazz_attack_11",
		"mp3": "/sounds/vo/dazzle/dazz_attack_11.mp3",
		"hero_id": 50,
		"voice_id": 50,
		"text": "Into my shadow!",
		"text_simple": " into my shadow ",
		"criteria": "Attack Isdazzle",
		"pretty_criteria": "Attacking"
	},
	{
		"name": "dazz_attack_12",
		"fullname": "dazzle_dazz_attack_12",
		"mp3": "/sounds/vo/dazzle/dazz_attack_12.mp3",
		"hero_id": 50,
		"voice_id": 50,
		"text": "For the order!",
		"text_simple": " for the order ",
		"criteria": "Attack Isdazzle",
		"pretty_criteria": "Attacking"
	},
	{
		"name": "dazz_attack_13",
		"fullname": "dazzle_dazz_attack_13",
		"mp3": "/sounds/vo/dazzle/dazz_attack_13.mp3",
		"hero_id": 50,
		"voice_id": 50,
		"text": "Ha ha!",
		"text_simple": " ha ha ",
		"criteria": "Attack Isdazzle",
		"pretty_criteria": "Attacking"
	},
	{
		"name": "dazz_cast_01",
		"fullname": "dazzle_dazz_cast_01",
		"mp3": "/sounds/vo/dazzle/dazz_cast_01.mp3",
		"hero_id": 50,
		"voice_id": 50,
		"text": "The shadow's cast!",
		"text_simple": " the shadows cast ",
		"criteria": "CastOrder Isdazzle",
		"pretty_criteria": "Ordered to cast an ability"
	},
	{
		"name": "dazz_cast_02",
		"fullname": "dazzle_dazz_cast_02",
		"mp3": "/sounds/vo/dazzle/dazz_cast_02.mp3",
		"hero_id": 50,
		"voice_id": 50,
		"text": "I follow like a shadow!",
		"text_simple": " i follow like a shadow ",
		"criteria": "CastOrder Isdazzle",
		"pretty_criteria": "Ordered to cast an ability"
	},
	{
		"name": "dazz_cast_03",
		"fullname": "dazzle_dazz_cast_03",
		"mp3": "/sounds/vo/dazzle/dazz_cast_03.mp3",
		"hero_id": 50,
		"voice_id": 50,
		"text": "Power of a priest!",
		"text_simple": " power of a priest ",
		"criteria": "CastOrder Isdazzle",
		"pretty_criteria": "Ordered to cast an ability"
	},
	{
		"name": "dazz_ability_poistouch_01",
		"fullname": "dazzle_dazz_ability_poistouch_01",
		"mp3": "/sounds/vo/dazzle/dazz_ability_poistouch_01.mp3",
		"hero_id": 50,
		"voice_id": 50,
		"text": "Feeling stricken?",
		"text_simple": " feeling stricken ",
		"pretty_criteria": "Unused"
	},
	{
		"name": "dazz_ability_poistouch_02",
		"fullname": "dazzle_dazz_ability_poistouch_02",
		"mp3": "/sounds/vo/dazzle/dazz_ability_poistouch_02.mp3",
		"hero_id": 50,
		"voice_id": 50,
		"text": "Just a touch.",
		"text_simple": " just a touch ",
		"criteria": "Powerup Isdazzle IsPowerupArcane",
		"pretty_criteria": "Activating an arcane rune"
	},
	{
		"name": "dazz_ability_poistouch_03",
		"fullname": "dazzle_dazz_ability_poistouch_03",
		"mp3": "/sounds/vo/dazzle/dazz_ability_poistouch_03.mp3",
		"hero_id": 50,
		"voice_id": 50,
		"text": "A touch of the old magic.",
		"text_simple": " a touch of the old magic ",
		"criteria": "Attack Isdazzle",
		"pretty_criteria": "Attacking"
	},
	{
		"name": "dazz_ability_shalgrave_05",
		"fullname": "dazzle_dazz_ability_shalgrave_05",
		"mp3": "/sounds/vo/dazzle/dazz_ability_shalgrave_05.mp3",
		"hero_id": 50,
		"voice_id": 50,
		"text": "Shadows keep you.",
		"text_simple": " shadows keep you ",
		"criteria": "Move Isdazzle",
		"pretty_criteria": "Moving"
	},
	{
		"name": "dazz_ability_shalgrave_08",
		"fullname": "dazzle_dazz_ability_shalgrave_08",
		"mp3": "/sounds/vo/dazzle/dazz_ability_shalgrave_08.mp3",
		"hero_id": 50,
		"voice_id": 50,
		"text": "Not while I'm around.",
		"text_simple": " not while im around ",
		"criteria": "CastOrder Isdazzle",
		"pretty_criteria": "Ordered to cast an ability"
	},
	{
		"name": "dazz_ability_shalgrave_01",
		"fullname": "dazzle_dazz_ability_shalgrave_01",
		"mp3": "/sounds/vo/dazzle/dazz_ability_shalgrave_01.mp3",
		"hero_id": 50,
		"voice_id": 50,
		"text": "Safe word!",
		"text_simple": " safe word ",
		"criteria": "CastExecute Isdazzle IsDazzleShallowGrave IsEnemyDazzle|CastExecute Isdazzle IsDazzleShallowGrave",
		"pretty_criteria": "Casting Shallow Grave on Dazzle|Casting Shallow Grave"
	},
	{
		"name": "dazz_ability_shalgrave_03",
		"fullname": "dazzle_dazz_ability_shalgrave_03",
		"mp3": "/sounds/vo/dazzle/dazz_ability_shalgrave_03.mp3",
		"hero_id": 50,
		"voice_id": 50,
		"text": "Not so fast!",
		"text_simple": " not so fast ",
		"criteria": "CastExecute Isdazzle IsDazzleShallowGrave IsEnemyDazzle|CastExecute Isdazzle IsDazzleShallowGrave",
		"pretty_criteria": "Casting Shallow Grave on Dazzle|Casting Shallow Grave"
	},
	{
		"name": "dazz_ability_shalgrave_10",
		"fullname": "dazzle_dazz_ability_shalgrave_10",
		"mp3": "/sounds/vo/dazzle/dazz_ability_shalgrave_10.mp3",
		"hero_id": 50,
		"voice_id": 50,
		"text": "Gravely mistaken.",
		"text_simple": " gravely mistaken ",
		"criteria": "CastExecute Isdazzle IsDazzleShallowGrave IsEnemyDazzle",
		"pretty_criteria": "Casting Shallow Grave on Dazzle"
	},
	{
		"name": "dazz_ability_shalgrave_02",
		"fullname": "dazzle_dazz_ability_shalgrave_02",
		"mp3": "/sounds/vo/dazzle/dazz_ability_shalgrave_02.mp3",
		"hero_id": 50,
		"voice_id": 50,
		"text": "You're safe!",
		"text_simple": " youre safe ",
		"criteria": "CastExecute Isdazzle IsDazzleShallowGrave",
		"pretty_criteria": "Casting Shallow Grave"
	},
	{
		"name": "dazz_ability_shalgrave_04",
		"fullname": "dazzle_dazz_ability_shalgrave_04",
		"mp3": "/sounds/vo/dazzle/dazz_ability_shalgrave_04.mp3",
		"hero_id": 50,
		"voice_id": 50,
		"text": "Bless you!",
		"text_simple": " bless you ",
		"criteria": "CastExecute Isdazzle IsDazzleShallowGrave",
		"pretty_criteria": "Casting Shallow Grave"
	},
	{
		"name": "dazz_ability_shalgrave_06",
		"fullname": "dazzle_dazz_ability_shalgrave_06",
		"mp3": "/sounds/vo/dazzle/dazz_ability_shalgrave_06.mp3",
		"hero_id": 50,
		"voice_id": 50,
		"text": "You're under my protection.",
		"text_simple": " youre under my protection ",
		"criteria": "CastExecute Isdazzle IsDazzleShallowGrave",
		"pretty_criteria": "Casting Shallow Grave"
	},
	{
		"name": "dazz_ability_shalgrave_07",
		"fullname": "dazzle_dazz_ability_shalgrave_07",
		"mp3": "/sounds/vo/dazzle/dazz_ability_shalgrave_07.mp3",
		"hero_id": 50,
		"voice_id": 50,
		"text": "You're safe with me.",
		"text_simple": " youre safe with me ",
		"criteria": "CastExecute Isdazzle IsDazzleShallowGrave",
		"pretty_criteria": "Casting Shallow Grave"
	},
	{
		"name": "dazz_ability_shalgrave_09",
		"fullname": "dazzle_dazz_ability_shalgrave_09",
		"mp3": "/sounds/vo/dazzle/dazz_ability_shalgrave_09.mp3",
		"hero_id": 50,
		"voice_id": 50,
		"text": "No grave for you.",
		"text_simple": " no grave for you ",
		"criteria": "CastExecute Isdazzle IsDazzleShallowGrave",
		"pretty_criteria": "Casting Shallow Grave"
	},
	{
		"name": "dazz_ability_shadowave_01",
		"fullname": "dazzle_dazz_ability_shadowave_01",
		"mp3": "/sounds/vo/dazzle/dazz_ability_shadowave_01.mp3",
		"hero_id": 50,
		"voice_id": 50,
		"text": "Zap!",
		"text_simple": " zap ",
		"criteria": "CastExecute Isdazzle IsDazzleShadowWave",
		"pretty_criteria": "Casting Shadow Wave"
	},
	{
		"name": "dazz_ability_shadowave_02",
		"fullname": "dazzle_dazz_ability_shadowave_02",
		"mp3": "/sounds/vo/dazzle/dazz_ability_shadowave_02.mp3",
		"hero_id": 50,
		"voice_id": 50,
		"text": "Jzap!",
		"text_simple": " jzap ",
		"criteria": "CastExecute Isdazzle IsDazzleShadowWave|HeroChatWheel GoldTier",
		"pretty_criteria": "Casting Shadow Wave|A gold hero chat wheel was used"
	},
	{
		"name": "dazz_ability_shadowave_03",
		"fullname": "dazzle_dazz_ability_shadowave_03",
		"mp3": "/sounds/vo/dazzle/dazz_ability_shadowave_03.mp3",
		"hero_id": 50,
		"voice_id": 50,
		"text": "Dazzle!",
		"text_simple": " dazzle ",
		"criteria": "CastExecute Isdazzle IsDazzleShadowWave",
		"pretty_criteria": "Casting Shadow Wave"
	},
	{
		"name": "dazz_ability_shadowave_04",
		"fullname": "dazzle_dazz_ability_shadowave_04",
		"mp3": "/sounds/vo/dazzle/dazz_ability_shadowave_04.mp3",
		"hero_id": 50,
		"voice_id": 50,
		"text": "Darklight!",
		"text_simple": " darklight ",
		"criteria": "CastExecute Isdazzle IsDazzleShadowWave",
		"pretty_criteria": "Casting Shadow Wave"
	},
	{
		"name": "dazz_ability_shadowave_05",
		"fullname": "dazzle_dazz_ability_shadowave_05",
		"mp3": "/sounds/vo/dazzle/dazz_ability_shadowave_05.mp3",
		"hero_id": 50,
		"voice_id": 50,
		"text": "Healing!",
		"text_simple": " healing ",
		"pretty_criteria": "Unused"
	},
	{
		"name": "dazz_ability_shadowave_06",
		"fullname": "dazzle_dazz_ability_shadowave_06",
		"mp3": "/sounds/vo/dazzle/dazz_ability_shadowave_06.mp3",
		"hero_id": 50,
		"voice_id": 50,
		"text": "You're in the pink!",
		"text_simple": " youre in the pink ",
		"pretty_criteria": "Unused"
	},
	{
		"name": "dazz_ability_shadowave_07",
		"fullname": "dazzle_dazz_ability_shadowave_07",
		"mp3": "/sounds/vo/dazzle/dazz_ability_shadowave_07.mp3",
		"hero_id": 50,
		"voice_id": 50,
		"text": "A healing glow!",
		"text_simple": " a healing glow ",
		"pretty_criteria": "Unused"
	},
	{
		"name": "dazz_ability_shadowave_08",
		"fullname": "dazzle_dazz_ability_shadowave_08",
		"mp3": "/sounds/vo/dazzle/dazz_ability_shadowave_08.mp3",
		"hero_id": 50,
		"voice_id": 50,
		"text": "Absolved!",
		"text_simple": " absolved ",
		"pretty_criteria": "Unused"
	},
	{
		"name": "dazz_ability_shadowave_09",
		"fullname": "dazzle_dazz_ability_shadowave_09",
		"mp3": "/sounds/vo/dazzle/dazz_ability_shadowave_09.mp3",
		"hero_id": 50,
		"voice_id": 50,
		"text": "Shadow wave!",
		"text_simple": " shadow wave ",
		"criteria": "CastExecute Isdazzle IsDazzleShadowWave",
		"pretty_criteria": "Casting Shadow Wave"
	},
	{
		"name": "dazz_ability_shadowave_10",
		"fullname": "dazzle_dazz_ability_shadowave_10",
		"mp3": "/sounds/vo/dazzle/dazz_ability_shadowave_10.mp3",
		"hero_id": 50,
		"voice_id": 50,
		"text": "Do the wave!",
		"text_simple": " do the wave ",
		"criteria": "CastExecute Isdazzle IsDazzleShadowWave",
		"pretty_criteria": "Casting Shadow Wave"
	},
	{
		"name": "dazz_ability_shadowave_11",
		"fullname": "dazzle_dazz_ability_shadowave_11",
		"mp3": "/sounds/vo/dazzle/dazz_ability_shadowave_11.mp3",
		"hero_id": 50,
		"voice_id": 50,
		"text": "Ask and you'll receive!",
		"text_simple": " ask and youll receive ",
		"criteria": "Move Isdazzle",
		"pretty_criteria": "Moving"
	},
	{
		"name": "dazz_ability_shadowave_12",
		"fullname": "dazzle_dazz_ability_shadowave_12",
		"mp3": "/sounds/vo/dazzle/dazz_ability_shadowave_12.mp3",
		"hero_id": 50,
		"voice_id": 50,
		"text": "So blessed!",
		"text_simple": " so blessed ",
		"criteria": "LevelUp Isdazzle",
		"pretty_criteria": "Leveling up"
	},
	{
		"name": "dazz_ability_weave_01",
		"fullname": "dazzle_dazz_ability_weave_01",
		"mp3": "/sounds/vo/dazzle/dazz_ability_weave_01.mp3",
		"hero_id": 50,
		"voice_id": 50,
		"text": "Ha ha ha ha yes!",
		"text_simple": " ha ha ha ha yes ",
		"pretty_criteria": "Unused"
	},
	{
		"name": "dazz_ability_weave_02",
		"fullname": "dazzle_dazz_ability_weave_02",
		"mp3": "/sounds/vo/dazzle/dazz_ability_weave_02.mp3",
		"hero_id": 50,
		"voice_id": 50,
		"text": "Yes!",
		"text_simple": " yes ",
		"criteria": "ItemDrop Isdazzle IsRareDrop",
		"pretty_criteria": "Recieving a rare cosmetic item"
	},
	{
		"name": "dazz_ability_weave_03",
		"fullname": "dazzle_dazz_ability_weave_03",
		"mp3": "/sounds/vo/dazzle/dazz_ability_weave_03.mp3",
		"hero_id": 50,
		"voice_id": 50,
		"text": "Ha ha!",
		"text_simple": " ha ha ",
		"criteria": "ItemDrop Isdazzle IsRareDrop",
		"pretty_criteria": "Recieving a rare cosmetic item"
	},
	{
		"name": "dazz_ability_weave_04",
		"fullname": "dazzle_dazz_ability_weave_04",
		"mp3": "/sounds/vo/dazzle/dazz_ability_weave_04.mp3",
		"hero_id": 50,
		"voice_id": 50,
		"text": "Zizzap!",
		"text_simple": " zizzap ",
		"pretty_criteria": "Unused"
	},
	{
		"name": "dazz_ability_weave_05",
		"fullname": "dazzle_dazz_ability_weave_05",
		"mp3": "/sounds/vo/dazzle/dazz_ability_weave_05.mp3",
		"hero_id": 50,
		"voice_id": 50,
		"text": "Buyap!",
		"text_simple": " buyap ",
		"pretty_criteria": "Unused"
	},
	{
		"name": "dazz_ability_weave_06",
		"fullname": "dazzle_dazz_ability_weave_06",
		"mp3": "/sounds/vo/dazzle/dazz_ability_weave_06.mp3",
		"hero_id": 50,
		"voice_id": 50,
		"text": "Ha ha!",
		"text_simple": " ha ha ",
		"pretty_criteria": "Unused"
	},
	{
		"name": "dazz_ability_weave_07",
		"fullname": "dazzle_dazz_ability_weave_07",
		"mp3": "/sounds/vo/dazzle/dazz_ability_weave_07.mp3",
		"hero_id": 50,
		"voice_id": 50,
		"text": "Rrrah! Ha ha ha!",
		"text_simple": " rrrah ha ha ha ",
		"pretty_criteria": "Unused"
	},
	{
		"name": "dazz_ability_sfx_01",
		"fullname": "dazzle_dazz_ability_sfx_01",
		"mp3": "/sounds/vo/dazzle/dazz_ability_sfx_01.mp3",
		"hero_id": 50,
		"voice_id": 50,
		"text": "Ngah!",
		"text_simple": " ngah ",
		"criteria": "CastExecute Isdazzle IsDazzlePoison",
		"pretty_criteria": "Casting Poison Touch"
	},
	{
		"name": "dazz_ability_sfx_02",
		"fullname": "dazzle_dazz_ability_sfx_02",
		"mp3": "/sounds/vo/dazzle/dazz_ability_sfx_02.mp3",
		"hero_id": 50,
		"voice_id": 50,
		"text": "Ya!",
		"text_simple": " ya ",
		"criteria": "CastExecute Isdazzle IsDazzlePoison",
		"pretty_criteria": "Casting Poison Touch"
	},
	{
		"name": "dazz_ability_sfx_03",
		"fullname": "dazzle_dazz_ability_sfx_03",
		"mp3": "/sounds/vo/dazzle/dazz_ability_sfx_03.mp3",
		"hero_id": 50,
		"voice_id": 50,
		"text": "Hrraarr!",
		"text_simple": " hrraarr ",
		"criteria": "CastExecute Isdazzle IsDazzlePoison",
		"pretty_criteria": "Casting Poison Touch"
	},
	{
		"name": "dazz_ability_sfx_04",
		"fullname": "dazzle_dazz_ability_sfx_04",
		"mp3": "/sounds/vo/dazzle/dazz_ability_sfx_04.mp3",
		"hero_id": 50,
		"voice_id": 50,
		"text": "Gra Ng!",
		"text_simple": " gra ng ",
		"criteria": "CastExecute Isdazzle IsDazzlePoison",
		"pretty_criteria": "Casting Poison Touch"
	},
	{
		"name": "dazz_ability_sfx_05",
		"fullname": "dazzle_dazz_ability_sfx_05",
		"mp3": "/sounds/vo/dazzle/dazz_ability_sfx_05.mp3",
		"hero_id": 50,
		"voice_id": 50,
		"text": "Guh!",
		"text_simple": " guh ",
		"criteria": "CastExecute Isdazzle IsDazzlePoison",
		"pretty_criteria": "Casting Poison Touch"
	},
	{
		"name": "dazz_ability_sfx_06",
		"fullname": "dazzle_dazz_ability_sfx_06",
		"mp3": "/sounds/vo/dazzle/dazz_ability_sfx_06.mp3",
		"hero_id": 50,
		"voice_id": 50,
		"text": "Hruh!",
		"text_simple": " hruh ",
		"criteria": "CastExecute Isdazzle IsDazzlePoison",
		"pretty_criteria": "Casting Poison Touch"
	},
	{
		"name": "dazz_ability_sfx_07",
		"fullname": "dazzle_dazz_ability_sfx_07",
		"mp3": "/sounds/vo/dazzle/dazz_ability_sfx_07.mp3",
		"hero_id": 50,
		"voice_id": 50,
		"text": "Hu-shaa!",
		"text_simple": " hushaa ",
		"criteria": "CastExecute Isdazzle IsDazzlePoison",
		"pretty_criteria": "Casting Poison Touch"
	},
	{
		"name": "dazz_ability_sfx_08",
		"fullname": "dazzle_dazz_ability_sfx_08",
		"mp3": "/sounds/vo/dazzle/dazz_ability_sfx_08.mp3",
		"hero_id": 50,
		"voice_id": 50,
		"text": "Dazzle!",
		"text_simple": " dazzle ",
		"criteria": "Powerup Isdazzle IsPowerupBounty",
		"pretty_criteria": "Activating a bounty rune"
	},
	{
		"name": "dazz_ability_sfx_09",
		"fullname": "dazzle_dazz_ability_sfx_09",
		"mp3": "/sounds/vo/dazzle/dazz_ability_sfx_09.mp3",
		"hero_id": 50,
		"voice_id": 50,
		"text": "Mmeh!",
		"text_simple": " mmeh ",
		"criteria": "CastExecute Isdazzle IsDazzlePoison",
		"pretty_criteria": "Casting Poison Touch"
	},
	{
		"name": "dazz_ability_sfx_10",
		"fullname": "dazzle_dazz_ability_sfx_10",
		"mp3": "/sounds/vo/dazzle/dazz_ability_sfx_10.mp3",
		"hero_id": 50,
		"voice_id": 50,
		"text": "Yes!",
		"text_simple": " yes ",
		"criteria": "CastExecute Isdazzle IsDazzlePoison",
		"pretty_criteria": "Casting Poison Touch"
	},
	{
		"name": "dazz_ability_sfx_11",
		"fullname": "dazzle_dazz_ability_sfx_11",
		"mp3": "/sounds/vo/dazzle/dazz_ability_sfx_11.mp3",
		"hero_id": 50,
		"voice_id": 50,
		"text": "Heh ha!",
		"text_simple": " heh ha ",
		"criteria": "CastExecute Isdazzle IsDazzlePoison",
		"pretty_criteria": "Casting Poison Touch"
	},
	{
		"name": "dazz_ability_sfx_12",
		"fullname": "dazzle_dazz_ability_sfx_12",
		"mp3": "/sounds/vo/dazzle/dazz_ability_sfx_12.mp3",
		"hero_id": 50,
		"voice_id": 50,
		"text": "Ha ha!",
		"text_simple": " ha ha ",
		"criteria": "CastExecute Isdazzle IsDazzlePoison",
		"pretty_criteria": "Casting Poison Touch"
	},
	{
		"name": "dazz_ability_sfx_13",
		"fullname": "dazzle_dazz_ability_sfx_13",
		"mp3": "/sounds/vo/dazzle/dazz_ability_sfx_13.mp3",
		"hero_id": 50,
		"voice_id": 50,
		"text": "Arr!",
		"text_simple": " arr ",
		"criteria": "CastExecute Isdazzle IsDazzlePoison",
		"pretty_criteria": "Casting Poison Touch"
	},
	{
		"name": "dazz_ability_sfx_14",
		"fullname": "dazzle_dazz_ability_sfx_14",
		"mp3": "/sounds/vo/dazzle/dazz_ability_sfx_14.mp3",
		"hero_id": 50,
		"voice_id": 50,
		"text": "Dazzle!",
		"text_simple": " dazzle ",
		"criteria": "Custom Isdazzle IsDazzleLoadoutSpawn|CastExecute Isdazzle IsDazzlePoison|Taunt Isdazzle IsDazzleTauntDazzlecopter",
		"pretty_criteria": "Spawning in the loadout|Casting Poison Touch|Taunting"
	},
	{
		"name": "dazz_ability_sfx_15",
		"fullname": "dazzle_dazz_ability_sfx_15",
		"mp3": "/sounds/vo/dazzle/dazz_ability_sfx_15.mp3",
		"hero_id": 50,
		"voice_id": 50,
		"text": "Hey oh!",
		"text_simple": " hey oh ",
		"criteria": "CastExecute Isdazzle IsDazzlePoison",
		"pretty_criteria": "Casting Poison Touch"
	},
	{
		"name": "dazz_level_01",
		"fullname": "dazzle_dazz_level_01",
		"mp3": "/sounds/vo/dazzle/dazz_level_01.mp3",
		"hero_id": 50,
		"voice_id": 50,
		"text": "Oh yes!",
		"text_simple": " oh yes ",
		"criteria": "LevelUp Isdazzle",
		"pretty_criteria": "Leveling up"
	},
	{
		"name": "dazz_level_02",
		"fullname": "dazzle_dazz_level_02",
		"mp3": "/sounds/vo/dazzle/dazz_level_02.mp3",
		"hero_id": 50,
		"voice_id": 50,
		"text": "Canonized!",
		"text_simple": " canonized ",
		"criteria": "LevelUp Isdazzle",
		"pretty_criteria": "Leveling up"
	},
	{
		"name": "dazz_level_03",
		"fullname": "dazzle_dazz_level_03",
		"mp3": "/sounds/vo/dazzle/dazz_level_03.mp3",
		"hero_id": 50,
		"voice_id": 50,
		"text": "A sacrament!",
		"text_simple": " a sacrament ",
		"criteria": "LevelUp Isdazzle",
		"pretty_criteria": "Leveling up"
	},
	{
		"name": "dazz_level_04",
		"fullname": "dazzle_dazz_level_04",
		"mp3": "/sounds/vo/dazzle/dazz_level_04.mp3",
		"hero_id": 50,
		"voice_id": 50,
		"text": "I renew my shady vows.",
		"text_simple": " i renew my shady vows ",
		"criteria": "LevelUp Isdazzle",
		"pretty_criteria": "Leveling up"
	},
	{
		"name": "dazz_level_05",
		"fullname": "dazzle_dazz_level_05",
		"mp3": "/sounds/vo/dazzle/dazz_level_05.mp3",
		"hero_id": 50,
		"voice_id": 50,
		"text": "I cast a long shadow.",
		"text_simple": " i cast a long shadow ",
		"criteria": "Custom Isdazzle IsDazzleLoadoutSpawn|LevelUp Isdazzle",
		"pretty_criteria": "Spawning in the loadout|Leveling up"
	},
	{
		"name": "dazz_level_06",
		"fullname": "dazzle_dazz_level_06",
		"mp3": "/sounds/vo/dazzle/dazz_level_06.mp3",
		"hero_id": 50,
		"voice_id": 50,
		"text": "Nga ah ha ha ha!",
		"text_simple": " nga ah ha ha ha ",
		"criteria": "LevelUp Isdazzle",
		"pretty_criteria": "Leveling up"
	},
	{
		"name": "dazz_kill_01",
		"fullname": "dazzle_dazz_kill_01",
		"mp3": "/sounds/vo/dazzle/dazz_kill_01.mp3",
		"hero_id": 50,
		"voice_id": 50,
		"text": "My congregation shrinks by one.",
		"text_simple": " my congregation shrinks by one ",
		"criteria": "Kill Isdazzle",
		"pretty_criteria": "Killing a hero"
	},
	{
		"name": "dazz_kill_02",
		"fullname": "dazzle_dazz_kill_02",
		"mp3": "/sounds/vo/dazzle/dazz_kill_02.mp3",
		"hero_id": 50,
		"voice_id": 50,
		"text": "I convey your spirit to the Nothl realm.",
		"text_simple": " i convey your spirit to the nothl realm ",
		"criteria": "Kill Isdazzle",
		"pretty_criteria": "Killing a hero"
	},
	{
		"name": "dazz_kill_03",
		"fullname": "dazzle_dazz_kill_03",
		"mp3": "/sounds/vo/dazzle/dazz_kill_03.mp3",
		"hero_id": 50,
		"voice_id": 50,
		"text": "I speak your final rites.",
		"text_simple": " i speak your final rites ",
		"criteria": "Kill Isdazzle",
		"pretty_criteria": "Killing a hero"
	},
	{
		"name": "dazz_kill_04",
		"fullname": "dazzle_dazz_kill_04",
		"mp3": "/sounds/vo/dazzle/dazz_kill_04.mp3",
		"hero_id": 50,
		"voice_id": 50,
		"text": "Where my shadow falls, there falls my foe.",
		"text_simple": " where my shadow falls there falls my foe ",
		"criteria": "Custom Isdazzle IsDazzleLoadoutSpawn|Kill Isdazzle",
		"pretty_criteria": "Spawning in the loadout|Killing a hero"
	},
	{
		"name": "dazz_kill_05",
		"fullname": "dazzle_dazz_kill_05",
		"mp3": "/sounds/vo/dazzle/dazz_kill_05.mp3",
		"hero_id": 50,
		"voice_id": 50,
		"text": "A dazzling death.",
		"text_simple": " a dazzling death ",
		"criteria": "Kill Isdazzle|HeroChatWheel SilverTier",
		"pretty_criteria": "Killing a hero|A silver hero chat wheel was used"
	},
	{
		"name": "dazz_kill_06",
		"fullname": "dazzle_dazz_kill_06",
		"mp3": "/sounds/vo/dazzle/dazz_kill_06.mp3",
		"hero_id": 50,
		"voice_id": 50,
		"text": "If killing you is wrong, I don't want to be right.",
		"text_simple": " if killing you is wrong i dont want to be right ",
		"criteria": "Kill Isdazzle|HeroChatWheel GrandmasterTier",
		"pretty_criteria": "Killing a hero|A grandmaster hero chat wheel was used"
	},
	{
		"name": "dazz_kill_07",
		"fullname": "dazzle_dazz_kill_07",
		"mp3": "/sounds/vo/dazzle/dazz_kill_07.mp3",
		"hero_id": 50,
		"voice_id": 50,
		"text": "Sacrificed to shadows.",
		"text_simple": " sacrificed to shadows ",
		"criteria": "Kill Isdazzle",
		"pretty_criteria": "Killing a hero"
	},
	{
		"name": "dazz_kill_08",
		"fullname": "dazzle_dazz_kill_08",
		"mp3": "/sounds/vo/dazzle/dazz_kill_08.mp3",
		"hero_id": 50,
		"voice_id": 50,
		"text": "Sanctioned by the order.",
		"text_simple": " sanctioned by the order ",
		"criteria": "Kill Isdazzle",
		"pretty_criteria": "Killing a hero"
	},
	{
		"name": "dazz_kill_09",
		"fullname": "dazzle_dazz_kill_09",
		"mp3": "/sounds/vo/dazzle/dazz_kill_09.mp3",
		"hero_id": 50,
		"voice_id": 50,
		"text": "Your death ennobles us all.",
		"text_simple": " your death ennobles us all ",
		"criteria": "Kill Isdazzle",
		"pretty_criteria": "Killing a hero"
	},
	{
		"name": "dazz_kill_10",
		"fullname": "dazzle_dazz_kill_10",
		"mp3": "/sounds/vo/dazzle/dazz_kill_10.mp3",
		"hero_id": 50,
		"voice_id": 50,
		"text": "Tricked you.",
		"text_simple": " tricked you ",
		"criteria": "Kill Isdazzle|HeroChatWheel PlatinumTier",
		"pretty_criteria": "Killing a hero|A platinum hero chat wheel was used"
	},
	{
		"name": "dazz_kill_11",
		"fullname": "dazzle_dazz_kill_11",
		"mp3": "/sounds/vo/dazzle/dazz_kill_11.mp3",
		"hero_id": 50,
		"voice_id": 50,
		"text": "You cast no shadow now.",
		"text_simple": " you cast no shadow now ",
		"criteria": "Kill Isdazzle",
		"pretty_criteria": "Killing a hero"
	},
	{
		"name": "dazz_kill_12",
		"fullname": "dazzle_dazz_kill_12",
		"mp3": "/sounds/vo/dazzle/dazz_kill_12.mp3",
		"hero_id": 50,
		"voice_id": 50,
		"text": "Ha ha!",
		"text_simple": " ha ha ",
		"criteria": "Kill Isdazzle",
		"pretty_criteria": "Killing a hero"
	},
	{
		"name": "dazz_rival_01",
		"fullname": "dazzle_dazz_rival_01",
		"mp3": "/sounds/vo/dazzle/dazz_rival_01.mp3",
		"hero_id": 50,
		"voice_id": 50,
		"text": "Heal yourself, doctor.",
		"text_simple": " heal yourself doctor ",
		"criteria": "Kill Isdazzle IsEnemyWitchDoctor Chance_50%",
		"pretty_criteria": "Killing Witch Doctor (50% chance)"
	},
	{
		"name": "dazz_rival_02",
		"fullname": "dazzle_dazz_rival_02",
		"mp3": "/sounds/vo/dazzle/dazz_rival_02.mp3",
		"hero_id": 50,
		"voice_id": 50,
		"text": "Curse you, Axe!",
		"text_simple": " curse you axe ",
		"criteria": "Kill Isdazzle IsEnemyAxe Chance_50%",
		"pretty_criteria": "Killing Axe (50% chance)"
	},
	{
		"name": "dazz_rival_03",
		"fullname": "dazzle_dazz_rival_03",
		"mp3": "/sounds/vo/dazzle/dazz_rival_03.mp3",
		"hero_id": 50,
		"voice_id": 50,
		"text": "Shadow Shaman, over the hills with you!",
		"text_simple": " shadow shaman over the hills with you ",
		"criteria": "Kill Isdazzle IsEnemyShadowShaman Chance_50%",
		"pretty_criteria": "Killing Shadow Shaman (50% chance)"
	},
	{
		"name": "dazz_death_01",
		"fullname": "dazzle_dazz_death_01",
		"mp3": "/sounds/vo/dazzle/dazz_death_01.mp3",
		"hero_id": 50,
		"voice_id": 50,
		"text": "No!",
		"text_simple": " no ",
		"criteria": "Death Isdazzle",
		"pretty_criteria": "Dying"
	},
	{
		"name": "dazz_death_02",
		"fullname": "dazzle_dazz_death_02",
		"mp3": "/sounds/vo/dazzle/dazz_death_02.mp3",
		"hero_id": 50,
		"voice_id": 50,
		"text": "My shadow falls.",
		"text_simple": " my shadow falls ",
		"criteria": "Death Isdazzle",
		"pretty_criteria": "Dying"
	},
	{
		"name": "dazz_death_03",
		"fullname": "dazzle_dazz_death_03",
		"mp3": "/sounds/vo/dazzle/dazz_death_03.mp3",
		"hero_id": 50,
		"voice_id": 50,
		"text": "By what right?",
		"text_simple": " by what right ",
		"criteria": "Death Isdazzle",
		"pretty_criteria": "Dying"
	},
	{
		"name": "dazz_death_04",
		"fullname": "dazzle_dazz_death_04",
		"mp3": "/sounds/vo/dazzle/dazz_death_04.mp3",
		"hero_id": 50,
		"voice_id": 50,
		"text": "My dazzle darkens.",
		"text_simple": " my dazzle darkens ",
		"criteria": "Death Isdazzle",
		"pretty_criteria": "Dying"
	},
	{
		"name": "dazz_death_05",
		"fullname": "dazzle_dazz_death_05",
		"mp3": "/sounds/vo/dazzle/dazz_death_05.mp3",
		"hero_id": 50,
		"voice_id": 50,
		"text": "Dazzling no more.",
		"text_simple": " dazzling no more ",
		"criteria": "Death Isdazzle",
		"pretty_criteria": "Dying"
	},
	{
		"name": "dazz_death_06",
		"fullname": "dazzle_dazz_death_06",
		"mp3": "/sounds/vo/dazzle/dazz_death_06.mp3",
		"hero_id": 50,
		"voice_id": 50,
		"text": "Death casts no shadow.",
		"text_simple": " death casts no shadow ",
		"criteria": "Death Isdazzle",
		"pretty_criteria": "Dying"
	},
	{
		"name": "dazz_death_07",
		"fullname": "dazzle_dazz_death_07",
		"mp3": "/sounds/vo/dazzle/dazz_death_07.mp3",
		"hero_id": 50,
		"voice_id": 50,
		"text": "Should have healed myself.",
		"text_simple": " should have healed myself ",
		"criteria": "Death Isdazzle",
		"pretty_criteria": "Dying"
	},
	{
		"name": "dazz_death_08",
		"fullname": "dazzle_dazz_death_08",
		"mp3": "/sounds/vo/dazzle/dazz_death_08.mp3",
		"hero_id": 50,
		"voice_id": 50,
		"text": "I was under orders.",
		"text_simple": " i was under orders ",
		"criteria": "Death Isdazzle",
		"pretty_criteria": "Dying"
	},
	{
		"name": "dazz_death_09",
		"fullname": "dazzle_dazz_death_09",
		"mp3": "/sounds/vo/dazzle/dazz_death_09.mp3",
		"hero_id": 50,
		"voice_id": 50,
		"text": "Excommunicated.",
		"text_simple": " excommunicated ",
		"criteria": "Death Isdazzle",
		"pretty_criteria": "Dying"
	},
	{
		"name": "dazz_death_10",
		"fullname": "dazzle_dazz_death_10",
		"mp3": "/sounds/vo/dazzle/dazz_death_10.mp3",
		"hero_id": 50,
		"voice_id": 50,
		"text": "Shadows take me.",
		"text_simple": " shadows take me ",
		"criteria": "Death Isdazzle",
		"pretty_criteria": "Dying"
	},
	{
		"name": "dazz_death_11",
		"fullname": "dazzle_dazz_death_11",
		"mp3": "/sounds/vo/dazzle/dazz_death_11.mp3",
		"hero_id": 50,
		"voice_id": 50,
		"text": "My shadow lost.",
		"text_simple": " my shadow lost ",
		"criteria": "Death Isdazzle",
		"pretty_criteria": "Dying"
	},
	{
		"name": "dazz_fastres_01",
		"fullname": "dazzle_dazz_fastres_01",
		"mp3": "/sounds/vo/dazzle/dazz_fastres_01.mp3",
		"hero_id": 50,
		"voice_id": 50,
		"text": "This death means nothing to me!",
		"text_simple": " this death means nothing to me ",
		"criteria": "Death Isdazzle IsReincarnating",
		"pretty_criteria": "Dying and respawning from aegis"
	},
	{
		"name": "dazz_respawn_01",
		"fullname": "dazzle_dazz_respawn_01",
		"mp3": "/sounds/vo/dazzle/dazz_respawn_01.mp3",
		"hero_id": 50,
		"voice_id": 50,
		"text": "That's no simple ordination.",
		"text_simple": " thats no simple ordination ",
		"criteria": "Respawn Isdazzle",
		"pretty_criteria": "Respawning"
	},
	{
		"name": "dazz_respawn_02",
		"fullname": "dazzle_dazz_respawn_02",
		"mp3": "/sounds/vo/dazzle/dazz_respawn_02.mp3",
		"hero_id": 50,
		"voice_id": 50,
		"text": "I never miss a trick.",
		"text_simple": " i never miss a trick ",
		"criteria": "Respawn Isdazzle",
		"pretty_criteria": "Respawning"
	},
	{
		"name": "dazz_respawn_03",
		"fullname": "dazzle_dazz_respawn_03",
		"mp3": "/sounds/vo/dazzle/dazz_respawn_03.mp3",
		"hero_id": 50,
		"voice_id": 50,
		"text": "I've been to the place where darkness is light.",
		"text_simple": " ive been to the place where darkness is light ",
		"criteria": "Respawn Isdazzle",
		"pretty_criteria": "Respawning"
	},
	{
		"name": "dazz_respawn_04",
		"fullname": "dazzle_dazz_respawn_04",
		"mp3": "/sounds/vo/dazzle/dazz_respawn_04.mp3",
		"hero_id": 50,
		"voice_id": 50,
		"text": "Up to my old tricks again.",
		"text_simple": " up to my old tricks again ",
		"criteria": "Custom Isdazzle IsDazzleLoadoutSpawn|Respawn Isdazzle",
		"pretty_criteria": "Spawning in the loadout|Respawning"
	},
	{
		"name": "dazz_respawn_05",
		"fullname": "dazzle_dazz_respawn_05",
		"mp3": "/sounds/vo/dazzle/dazz_respawn_05.mp3",
		"hero_id": 50,
		"voice_id": 50,
		"text": "Returned from Nothl's realm.",
		"text_simple": " returned from nothls realm ",
		"criteria": "Respawn Isdazzle",
		"pretty_criteria": "Respawning"
	},
	{
		"name": "dazz_respawn_06",
		"fullname": "dazzle_dazz_respawn_06",
		"mp3": "/sounds/vo/dazzle/dazz_respawn_06.mp3",
		"hero_id": 50,
		"voice_id": 50,
		"text": "I await new orders.",
		"text_simple": " i await new orders ",
		"criteria": "Respawn Isdazzle",
		"pretty_criteria": "Respawning"
	},
	{
		"name": "dazz_respawn_07",
		"fullname": "dazzle_dazz_respawn_07",
		"mp3": "/sounds/vo/dazzle/dazz_respawn_07.mp3",
		"hero_id": 50,
		"voice_id": 50,
		"text": "Reordained.",
		"text_simple": " reordained ",
		"criteria": "Respawn Isdazzle",
		"pretty_criteria": "Respawning"
	},
	{
		"name": "dazz_respawn_08",
		"fullname": "dazzle_dazz_respawn_08",
		"mp3": "/sounds/vo/dazzle/dazz_respawn_08.mp3",
		"hero_id": 50,
		"voice_id": 50,
		"text": "More dazzling than ever.",
		"text_simple": " more dazzling than ever ",
		"criteria": "Respawn Isdazzle",
		"pretty_criteria": "Respawning"
	},
	{
		"name": "dazz_respawn_09",
		"fullname": "dazzle_dazz_respawn_09",
		"mp3": "/sounds/vo/dazzle/dazz_respawn_09.mp3",
		"hero_id": 50,
		"voice_id": 50,
		"text": "That was almost a disaster.",
		"text_simple": " that was almost a disaster ",
		"criteria": "Respawn Isdazzle|HeroChatWheel MasterTier",
		"pretty_criteria": "Respawning|A master hero chat wheel was used"
	},
	{
		"name": "dazz_respawn_10",
		"fullname": "dazzle_dazz_respawn_10",
		"mp3": "/sounds/vo/dazzle/dazz_respawn_10.mp3",
		"hero_id": 50,
		"voice_id": 50,
		"text": "Resurrection comes easily to a Shadow Priest!",
		"text_simple": " resurrection comes easily to a shadow priest ",
		"criteria": "Respawn Isdazzle",
		"pretty_criteria": "Respawning"
	},
	{
		"name": "dazz_lasthit_01",
		"fullname": "dazzle_dazz_lasthit_01",
		"mp3": "/sounds/vo/dazzle/dazz_lasthit_01.mp3",
		"hero_id": 50,
		"voice_id": 50,
		"text": "Dazzled!",
		"text_simple": " dazzled ",
		"criteria": "LastHit Isdazzle",
		"pretty_criteria": "Last hitting"
	},
	{
		"name": "dazz_lasthit_02",
		"fullname": "dazzle_dazz_lasthit_02",
		"mp3": "/sounds/vo/dazzle/dazz_lasthit_02.mp3",
		"hero_id": 50,
		"voice_id": 50,
		"text": "Huh huh pretty!",
		"text_simple": " huh huh pretty ",
		"criteria": "LastHit Isdazzle",
		"pretty_criteria": "Last hitting"
	},
	{
		"name": "dazz_lasthit_03",
		"fullname": "dazzle_dazz_lasthit_03",
		"mp3": "/sounds/vo/dazzle/dazz_lasthit_03.mp3",
		"hero_id": 50,
		"voice_id": 50,
		"text": "Saved!",
		"text_simple": " saved ",
		"criteria": "LastHit Isdazzle",
		"pretty_criteria": "Last hitting"
	},
	{
		"name": "dazz_lasthit_04",
		"fullname": "dazzle_dazz_lasthit_04",
		"mp3": "/sounds/vo/dazzle/dazz_lasthit_04.mp3",
		"hero_id": 50,
		"voice_id": 50,
		"text": "Shiny!",
		"text_simple": " shiny ",
		"criteria": "LastHit Isdazzle",
		"pretty_criteria": "Last hitting"
	},
	{
		"name": "dazz_lasthit_05",
		"fullname": "dazzle_dazz_lasthit_05",
		"mp3": "/sounds/vo/dazzle/dazz_lasthit_05.mp3",
		"hero_id": 50,
		"voice_id": 50,
		"text": "A weak offering!",
		"text_simple": " a weak offering ",
		"criteria": "LastHit Isdazzle",
		"pretty_criteria": "Last hitting"
	},
	{
		"name": "dazz_lasthit_06",
		"fullname": "dazzle_dazz_lasthit_06",
		"mp3": "/sounds/vo/dazzle/dazz_lasthit_06.mp3",
		"hero_id": 50,
		"voice_id": 50,
		"text": "Alms from the dead!",
		"text_simple": " alms from the dead ",
		"criteria": "LastHit Isdazzle",
		"pretty_criteria": "Last hitting"
	},
	{
		"name": "dazz_lasthit_07",
		"fullname": "dazzle_dazz_lasthit_07",
		"mp3": "/sounds/vo/dazzle/dazz_lasthit_07.mp3",
		"hero_id": 50,
		"voice_id": 50,
		"text": "Collected!",
		"text_simple": " collected ",
		"criteria": "LastHit Isdazzle",
		"pretty_criteria": "Last hitting"
	},
	{
		"name": "dazz_lasthit_08",
		"fullname": "dazzle_dazz_lasthit_08",
		"mp3": "/sounds/vo/dazzle/dazz_lasthit_08.mp3",
		"hero_id": 50,
		"voice_id": 50,
		"text": "Charitable of you.",
		"text_simple": " charitable of you ",
		"criteria": "LastHit Isdazzle|HeroChatWheel GoldTier",
		"pretty_criteria": "Last hitting|A gold hero chat wheel was used"
	},
	{
		"name": "dazz_lasthit_09",
		"fullname": "dazzle_dazz_lasthit_09",
		"mp3": "/sounds/vo/dazzle/dazz_lasthit_09.mp3",
		"hero_id": 50,
		"voice_id": 50,
		"text": "Pretty!",
		"text_simple": " pretty ",
		"criteria": "LastHit Isdazzle",
		"pretty_criteria": "Last hitting"
	},
	{
		"name": "dazz_deny_01",
		"fullname": "dazzle_dazz_deny_01",
		"mp3": "/sounds/vo/dazzle/dazz_deny_01.mp3",
		"hero_id": 50,
		"voice_id": 50,
		"text": "Denied!",
		"text_simple": " denied ",
		"criteria": "Deny Isdazzle",
		"pretty_criteria": "Denying"
	},
	{
		"name": "dazz_deny_02",
		"fullname": "dazzle_dazz_deny_02",
		"mp3": "/sounds/vo/dazzle/dazz_deny_02.mp3",
		"hero_id": 50,
		"voice_id": 50,
		"text": "Denied!",
		"text_simple": " denied ",
		"criteria": "Deny Isdazzle",
		"pretty_criteria": "Denying"
	},
	{
		"name": "dazz_deny_03",
		"fullname": "dazzle_dazz_deny_03",
		"mp3": "/sounds/vo/dazzle/dazz_deny_03.mp3",
		"hero_id": 50,
		"voice_id": 50,
		"text": "Uh uh.",
		"text_simple": " uh uh ",
		"criteria": "Deny Isdazzle",
		"pretty_criteria": "Denying"
	},
	{
		"name": "dazz_deny_04",
		"fullname": "dazzle_dazz_deny_04",
		"mp3": "/sounds/vo/dazzle/dazz_deny_04.mp3",
		"hero_id": 50,
		"voice_id": 50,
		"text": "Get back.",
		"text_simple": " get back ",
		"criteria": "Deny Isdazzle",
		"pretty_criteria": "Denying"
	},
	{
		"name": "dazz_deny_05",
		"fullname": "dazzle_dazz_deny_05",
		"mp3": "/sounds/vo/dazzle/dazz_deny_05.mp3",
		"hero_id": 50,
		"voice_id": 50,
		"text": "No way.",
		"text_simple": " no way ",
		"criteria": "Deny Isdazzle",
		"pretty_criteria": "Denying"
	},
	{
		"name": "dazz_deny_06",
		"fullname": "dazzle_dazz_deny_06",
		"mp3": "/sounds/vo/dazzle/dazz_deny_06.mp3",
		"hero_id": 50,
		"voice_id": 50,
		"text": "Wrong!",
		"text_simple": " wrong ",
		"criteria": "Deny Isdazzle",
		"pretty_criteria": "Denying"
	},
	{
		"name": "dazz_deny_07",
		"fullname": "dazzle_dazz_deny_07",
		"mp3": "/sounds/vo/dazzle/dazz_deny_07.mp3",
		"hero_id": 50,
		"voice_id": 50,
		"text": "You've no right!",
		"text_simple": " youve no right ",
		"criteria": "Deny Isdazzle",
		"pretty_criteria": "Denying"
	},
	{
		"name": "dazz_deny_08",
		"fullname": "dazzle_dazz_deny_08",
		"mp3": "/sounds/vo/dazzle/dazz_deny_08.mp3",
		"hero_id": 50,
		"voice_id": 50,
		"text": "That's not right.",
		"text_simple": " thats not right ",
		"criteria": "Deny Isdazzle|HeroChatWheel SilverTier",
		"pretty_criteria": "Denying|A silver hero chat wheel was used"
	},
	{
		"name": "dazz_deny_09",
		"fullname": "dazzle_dazz_deny_09",
		"mp3": "/sounds/vo/dazzle/dazz_deny_09.mp3",
		"hero_id": 50,
		"voice_id": 50,
		"text": "Hm hm ha ha ha ha!",
		"text_simple": " hm hm ha ha ha ha ",
		"criteria": "Deny Isdazzle",
		"pretty_criteria": "Denying"
	},
	{
		"name": "dazz_deny_10",
		"fullname": "dazzle_dazz_deny_10",
		"mp3": "/sounds/vo/dazzle/dazz_deny_10.mp3",
		"hero_id": 50,
		"voice_id": 50,
		"text": "Ha ha ha!",
		"text_simple": " ha ha ha ",
		"criteria": "Deny Isdazzle",
		"pretty_criteria": "Denying"
	},
	{
		"name": "dazz_rare_01",
		"fullname": "dazzle_dazz_rare_01",
		"mp3": "/sounds/vo/dazzle/dazz_rare_01.mp3",
		"hero_id": 50,
		"voice_id": 50,
		"text": "I've seen the blinding darkness at the center of all light.",
		"text_simple": " ive seen the blinding darkness at the center of all light ",
		"criteria": "Select Isdazzle",
		"pretty_criteria": "Rare"
	},
	{
		"name": "dazz_rare_02",
		"fullname": "dazzle_dazz_rare_02",
		"mp3": "/sounds/vo/dazzle/dazz_rare_02.mp3",
		"hero_id": 50,
		"voice_id": 50,
		"text": "In the Nothl realm, brightness is dark, and the touch that heals a friend will fell a foe.",
		"text_simple": " in the nothl realm brightness is dark and the touch that heals a friend will fell a foe ",
		"criteria": "Select Isdazzle",
		"pretty_criteria": "Rare"
	},
	{
		"name": "dazz_purch_01",
		"fullname": "dazzle_dazz_purch_01",
		"mp3": "/sounds/vo/dazzle/dazz_purch_01.mp3",
		"hero_id": 50,
		"voice_id": 50,
		"text": "I'd set aside funds for this.",
		"text_simple": " id set aside funds for this ",
		"criteria": "Purchase Isdazzle IsExpensiveItem",
		"pretty_criteria": "Buying an expensive item"
	},
	{
		"name": "dazz_purch_02",
		"fullname": "dazzle_dazz_purch_02",
		"mp3": "/sounds/vo/dazzle/dazz_purch_02.mp3",
		"hero_id": 50,
		"voice_id": 50,
		"text": "Ah, my order is in!",
		"text_simple": " ah my order is in ",
		"criteria": "Purchase Isdazzle IsExpensiveItem",
		"pretty_criteria": "Buying an expensive item"
	},
	{
		"name": "dazz_purch_03",
		"fullname": "dazzle_dazz_purch_03",
		"mp3": "/sounds/vo/dazzle/dazz_purch_03.mp3",
		"hero_id": 50,
		"voice_id": 50,
		"text": "Oh, what a beauty!",
		"text_simple": " oh what a beauty ",
		"criteria": "Purchase Isdazzle IsExpensiveItem|HeroChatWheel BronzeTier",
		"pretty_criteria": "Buying an expensive item|A bronze hero chat wheel was used"
	},
	{
		"name": "dazz_blink_01",
		"fullname": "dazzle_dazz_blink_01",
		"mp3": "/sounds/vo/dazzle/dazz_blink_01.mp3",
		"hero_id": 50,
		"voice_id": 50,
		"text": "Blink dagger!",
		"text_simple": " blink dagger ",
		"criteria": "Purchase Isdazzle IsBlinkDagger",
		"pretty_criteria": "Buying Blink Dagger"
	},
	{
		"name": "dazz_blink_02",
		"fullname": "dazzle_dazz_blink_02",
		"mp3": "/sounds/vo/dazzle/dazz_blink_02.mp3",
		"hero_id": 50,
		"voice_id": 50,
		"text": "The dagger that dazzles.",
		"text_simple": " the dagger that dazzles ",
		"criteria": "Purchase Isdazzle IsBlinkDagger",
		"pretty_criteria": "Buying Blink Dagger"
	},
	{
		"name": "dazz_scepter_01",
		"fullname": "dazzle_dazz_scepter_01",
		"mp3": "/sounds/vo/dazzle/dazz_scepter_01.mp3",
		"hero_id": 50,
		"voice_id": 50,
		"text": "Ah, Scepter!",
		"text_simple": " ah scepter ",
		"criteria": "Purchase Isdazzle IsUltimateScepter",
		"pretty_criteria": "Buying Aghanim's Scepter"
	},
	{
		"name": "dazz_scepter_02",
		"fullname": "dazzle_dazz_scepter_02",
		"mp3": "/sounds/vo/dazzle/dazz_scepter_02.mp3",
		"hero_id": 50,
		"voice_id": 50,
		"text": "Sacred scepter!",
		"text_simple": " sacred scepter ",
		"criteria": "Purchase Isdazzle IsUltimateScepter",
		"pretty_criteria": "Buying Aghanim's Scepter"
	},
	{
		"name": "dazz_item_01",
		"fullname": "dazzle_dazz_item_01",
		"mp3": "/sounds/vo/dazzle/dazz_item_01.mp3",
		"hero_id": 50,
		"voice_id": 50,
		"text": "Oh, sacred Mekansm!",
		"text_simple": " oh sacred mekansm ",
		"criteria": "Purchase Isdazzle IsMekansm",
		"pretty_criteria": "Buying Mekansm"
	},
	{
		"name": "dazz_item_02",
		"fullname": "dazzle_dazz_item_02",
		"mp3": "/sounds/vo/dazzle/dazz_item_02.mp3",
		"hero_id": 50,
		"voice_id": 50,
		"text": "Shiva's Guard, to guard us well!",
		"text_simple": " shivas guard to guard us well ",
		"criteria": "Purchase Isdazzle IsShiva",
		"pretty_criteria": "Buying Shiva's Guard"
	},
	{
		"name": "dazz_item_03",
		"fullname": "dazzle_dazz_item_03",
		"mp3": "/sounds/vo/dazzle/dazz_item_03.mp3",
		"hero_id": 50,
		"voice_id": 50,
		"text": "Desolator!",
		"text_simple": " desolator ",
		"criteria": "Purchase Isdazzle IsDesolator",
		"pretty_criteria": "Buying Desolator"
	},
	{
		"name": "dazz_bottle_01",
		"fullname": "dazzle_dazz_bottle_01",
		"mp3": "/sounds/vo/dazzle/dazz_bottle_01.mp3",
		"hero_id": 50,
		"voice_id": 50,
		"text": "Zip it up!",
		"text_simple": " zip it up ",
		"criteria": "Bottling Isdazzle",
		"pretty_criteria": "Bottling a rune"
	},
	{
		"name": "dazz_bottle_02",
		"fullname": "dazzle_dazz_bottle_02",
		"mp3": "/sounds/vo/dazzle/dazz_bottle_02.mp3",
		"hero_id": 50,
		"voice_id": 50,
		"text": "Caught the buzz!",
		"text_simple": " caught the buzz ",
		"criteria": "Bottling Isdazzle",
		"pretty_criteria": "Bottling a rune"
	},
	{
		"name": "dazz_bottle_03",
		"fullname": "dazzle_dazz_bottle_03",
		"mp3": "/sounds/vo/dazzle/dazz_bottle_03.mp3",
		"hero_id": 50,
		"voice_id": 50,
		"text": "Corked it.",
		"text_simple": " corked it ",
		"criteria": "Bottling Isdazzle",
		"pretty_criteria": "Bottling a rune"
	},
	{
		"name": "dazz_immort_01",
		"fullname": "dazzle_dazz_immort_01",
		"mp3": "/sounds/vo/dazzle/dazz_immort_01.mp3",
		"hero_id": 50,
		"voice_id": 50,
		"text": "Immortality!",
		"text_simple": " immortality ",
		"criteria": "Immortality Isdazzle",
		"pretty_criteria": "Grabbing aegis"
	},
	{
		"name": "dazz_immort_02",
		"fullname": "dazzle_dazz_immort_02",
		"mp3": "/sounds/vo/dazzle/dazz_immort_02.mp3",
		"hero_id": 50,
		"voice_id": 50,
		"text": "Death shall not shadow me.",
		"text_simple": " death shall not shadow me ",
		"criteria": "Immortality Isdazzle Chance_25%",
		"pretty_criteria": "Grabbing aegis (25% chance)"
	},
	{
		"name": "dazz_haste_01",
		"fullname": "dazzle_dazz_haste_01",
		"mp3": "/sounds/vo/dazzle/dazz_haste_01.mp3",
		"hero_id": 50,
		"voice_id": 50,
		"text": "Haste!",
		"text_simple": " haste ",
		"criteria": "Powerup Isdazzle IsPowerupHaste",
		"pretty_criteria": "Activating a haste rune"
	},
	{
		"name": "dazz_haste_02",
		"fullname": "dazzle_dazz_haste_02",
		"mp3": "/sounds/vo/dazzle/dazz_haste_02.mp3",
		"hero_id": 50,
		"voice_id": 50,
		"text": "The shadow speeds along!",
		"text_simple": " the shadow speeds along ",
		"pretty_criteria": "Unused"
	},
	{
		"name": "dazz_doubdam_01",
		"fullname": "dazzle_dazz_doubdam_01",
		"mp3": "/sounds/vo/dazzle/dazz_doubdam_01.mp3",
		"hero_id": 50,
		"voice_id": 50,
		"text": "Double damage!",
		"text_simple": " double damage ",
		"criteria": "Powerup Isdazzle IsPowerupDoubleDamage",
		"pretty_criteria": "Activating a double damage rune"
	},
	{
		"name": "dazz_doubdam_02",
		"fullname": "dazzle_dazz_doubdam_02",
		"mp3": "/sounds/vo/dazzle/dazz_doubdam_02.mp3",
		"hero_id": 50,
		"voice_id": 50,
		"text": "Double deity.",
		"text_simple": " double deity ",
		"criteria": "Powerup Isdazzle IsPowerupDoubleDamage Chance_25%",
		"pretty_criteria": "Activating a double damage rune (25% chance)"
	},
	{
		"name": "dazz_regen_01",
		"fullname": "dazzle_dazz_regen_01",
		"mp3": "/sounds/vo/dazzle/dazz_regen_01.mp3",
		"hero_id": 50,
		"voice_id": 50,
		"text": "Regeneration!",
		"text_simple": " regeneration ",
		"criteria": "Powerup Isdazzle IsPowerupRegeneration",
		"pretty_criteria": "Activating a regeneration rune"
	},
	{
		"name": "dazz_regen_02",
		"fullname": "dazzle_dazz_regen_02",
		"mp3": "/sounds/vo/dazzle/dazz_regen_02.mp3",
		"hero_id": 50,
		"voice_id": 50,
		"text": "Healing for the healer.",
		"text_simple": " healing for the healer ",
		"pretty_criteria": "Unused"
	},
	{
		"name": "dazz_illus_01",
		"fullname": "dazzle_dazz_illus_01",
		"mp3": "/sounds/vo/dazzle/dazz_illus_01.mp3",
		"hero_id": 50,
		"voice_id": 50,
		"text": "Illusion!",
		"text_simple": " illusion ",
		"criteria": "Powerup Isdazzle IsPowerupIllusion",
		"pretty_criteria": "Activating an illusion rune"
	},
	{
		"name": "dazz_illus_02",
		"fullname": "dazzle_dazz_illus_02",
		"mp3": "/sounds/vo/dazzle/dazz_illus_02.mp3",
		"hero_id": 50,
		"voice_id": 50,
		"text": "The threefold shadow.",
		"text_simple": " the threefold shadow ",
		"pretty_criteria": "Unused"
	},
	{
		"name": "dazz_invis_01",
		"fullname": "dazzle_dazz_invis_01",
		"mp3": "/sounds/vo/dazzle/dazz_invis_01.mp3",
		"hero_id": 50,
		"voice_id": 50,
		"text": "Invisibility!",
		"text_simple": " invisibility ",
		"criteria": "Powerup Isdazzle IsPowerupInvisibility",
		"pretty_criteria": "Activating an invisibility rune"
	},
	{
		"name": "dazz_invis_02",
		"fullname": "dazzle_dazz_invis_02",
		"mp3": "/sounds/vo/dazzle/dazz_invis_02.mp3",
		"hero_id": 50,
		"voice_id": 50,
		"text": "Shadows unseen!",
		"text_simple": " shadows unseen ",
		"pretty_criteria": "Unused"
	},
	{
		"name": "dazz_thanks_01",
		"fullname": "dazzle_dazz_thanks_01",
		"mp3": "/sounds/vo/dazzle/dazz_thanks_01.mp3",
		"hero_id": 50,
		"voice_id": 50,
		"text": "Thanks.",
		"text_simple": " thanks ",
		"criteria": "Thanks Isdazzle",
		"pretty_criteria": "Thanking"
	},
	{
		"name": "dazz_thanks_02",
		"fullname": "dazzle_dazz_thanks_02",
		"mp3": "/sounds/vo/dazzle/dazz_thanks_02.mp3",
		"hero_id": 50,
		"voice_id": 50,
		"text": "My gratitude.",
		"text_simple": " my gratitude ",
		"criteria": "Thanks Isdazzle",
		"pretty_criteria": "Thanking"
	},
	{
		"name": "dazz_underattack_01",
		"fullname": "dazzle_dazz_underattack_01",
		"mp3": "/sounds/vo/dazzle/dazz_underattack_01.mp3",
		"hero_id": 50,
		"voice_id": 50,
		"text": "I'm under attack!",
		"text_simple": " im under attack ",
		"criteria": "Pain Isdazzle Chance_25%",
		"pretty_criteria": "Taking damage (25% chance)"
	},
	{
		"name": "dazz_inthebag_01",
		"fullname": "dazzle_dazz_inthebag_01",
		"mp3": "/sounds/vo/dazzle/dazz_inthebag_01.mp3",
		"hero_id": 50,
		"voice_id": 50,
		"text": "It's in the bag!",
		"text_simple": " its in the bag ",
		"criteria": "InTheBag Isdazzle",
		"pretty_criteria": "In-the-bag"
	},
	{
		"name": "dazz_shitwiz_01",
		"fullname": "dazzle_dazz_shitwiz_01",
		"mp3": "/sounds/vo/dazzle/dazz_shitwiz_01.mp3",
		"hero_id": 50,
		"voice_id": 50,
		"text": "Shitty wizard!",
		"text_simple": " shitty wizard ",
		"pretty_criteria": "Unused"
	},
	{
		"name": "dazz_crumwiz_01",
		"fullname": "dazzle_dazz_crumwiz_01",
		"mp3": "/sounds/vo/dazzle/dazz_crumwiz_01.mp3",
		"hero_id": 50,
		"voice_id": 50,
		"text": "Crummy wizard!",
		"text_simple": " crummy wizard ",
		"pretty_criteria": "Unused"
	},
	{
		"name": "dazz_notyet_01",
		"fullname": "dazzle_dazz_notyet_01",
		"mp3": "/sounds/vo/dazzle/dazz_notyet_01.mp3",
		"hero_id": 50,
		"voice_id": 50,
		"text": "Not yet.",
		"text_simple": " not yet ",
		"criteria": "Cooldown Isdazzle LittleNag",
		"pretty_criteria": "Item/Ability on cooldown"
	},
	{
		"name": "dazz_notyet_02",
		"fullname": "dazzle_dazz_notyet_02",
		"mp3": "/sounds/vo/dazzle/dazz_notyet_02.mp3",
		"hero_id": 50,
		"voice_id": 50,
		"text": "I'm not ready.",
		"text_simple": " im not ready ",
		"criteria": "Cooldown Isdazzle LittleNag",
		"pretty_criteria": "Item/Ability on cooldown"
	},
	{
		"name": "dazz_notyet_03",
		"fullname": "dazzle_dazz_notyet_03",
		"mp3": "/sounds/vo/dazzle/dazz_notyet_03.mp3",
		"hero_id": 50,
		"voice_id": 50,
		"text": "It's not time yet.",
		"text_simple": " its not time yet ",
		"criteria": "Cooldown Isdazzle LittleNag",
		"pretty_criteria": "Item/Ability on cooldown"
	},
	{
		"name": "dazz_notyet_04",
		"fullname": "dazzle_dazz_notyet_04",
		"mp3": "/sounds/vo/dazzle/dazz_notyet_04.mp3",
		"hero_id": 50,
		"voice_id": 50,
		"text": "Not yet.",
		"text_simple": " not yet ",
		"criteria": "Cooldown Isdazzle MediumNag",
		"pretty_criteria": "Item/Ability on cooldown (medium naggy)"
	},
	{
		"name": "dazz_notyet_05",
		"fullname": "dazzle_dazz_notyet_05",
		"mp3": "/sounds/vo/dazzle/dazz_notyet_05.mp3",
		"hero_id": 50,
		"voice_id": 50,
		"text": "I'm not ready.",
		"text_simple": " im not ready ",
		"criteria": "Cooldown Isdazzle MediumNag",
		"pretty_criteria": "Item/Ability on cooldown (medium naggy)"
	},
	{
		"name": "dazz_notyet_06",
		"fullname": "dazzle_dazz_notyet_06",
		"mp3": "/sounds/vo/dazzle/dazz_notyet_06.mp3",
		"hero_id": 50,
		"voice_id": 50,
		"text": "It's not time yet.",
		"text_simple": " its not time yet ",
		"criteria": "Cooldown Isdazzle MediumNag",
		"pretty_criteria": "Item/Ability on cooldown (medium naggy)"
	},
	{
		"name": "dazz_notyet_07",
		"fullname": "dazzle_dazz_notyet_07",
		"mp3": "/sounds/vo/dazzle/dazz_notyet_07.mp3",
		"hero_id": 50,
		"voice_id": 50,
		"text": "Not yet.",
		"text_simple": " not yet ",
		"criteria": "Cooldown Isdazzle SuperNag",
		"pretty_criteria": "Item/Ability on cooldown (very naggy)"
	},
	{
		"name": "dazz_notyet_08",
		"fullname": "dazzle_dazz_notyet_08",
		"mp3": "/sounds/vo/dazzle/dazz_notyet_08.mp3",
		"hero_id": 50,
		"voice_id": 50,
		"text": "I'm not ready.",
		"text_simple": " im not ready ",
		"criteria": "Cooldown Isdazzle SuperNag",
		"pretty_criteria": "Item/Ability on cooldown (very naggy)"
	},
	{
		"name": "dazz_notyet_09",
		"fullname": "dazzle_dazz_notyet_09",
		"mp3": "/sounds/vo/dazzle/dazz_notyet_09.mp3",
		"hero_id": 50,
		"voice_id": 50,
		"text": "It's not time yet.",
		"text_simple": " its not time yet ",
		"criteria": "Cooldown Isdazzle SuperNag",
		"pretty_criteria": "Item/Ability on cooldown (very naggy)"
	},
	{
		"name": "dazz_nomana_01",
		"fullname": "dazzle_dazz_nomana_01",
		"mp3": "/sounds/vo/dazzle/dazz_nomana_01.mp3",
		"hero_id": 50,
		"voice_id": 50,
		"text": "Out of mana.",
		"text_simple": " out of mana ",
		"criteria": "NoMana Isdazzle LittleNag",
		"pretty_criteria": "Not enough mana"
	},
	{
		"name": "dazz_nomana_02",
		"fullname": "dazzle_dazz_nomana_02",
		"mp3": "/sounds/vo/dazzle/dazz_nomana_02.mp3",
		"hero_id": 50,
		"voice_id": 50,
		"text": "No mana.",
		"text_simple": " no mana ",
		"criteria": "NoMana Isdazzle LittleNag",
		"pretty_criteria": "Not enough mana"
	},
	{
		"name": "dazz_nomana_03",
		"fullname": "dazzle_dazz_nomana_03",
		"mp3": "/sounds/vo/dazzle/dazz_nomana_03.mp3",
		"hero_id": 50,
		"voice_id": 50,
		"text": "Not enough mana.",
		"text_simple": " not enough mana ",
		"criteria": "NoMana Isdazzle LittleNag",
		"pretty_criteria": "Not enough mana"
	},
	{
		"name": "dazz_nomana_04",
		"fullname": "dazzle_dazz_nomana_04",
		"mp3": "/sounds/vo/dazzle/dazz_nomana_04.mp3",
		"hero_id": 50,
		"voice_id": 50,
		"text": "Out of mana.",
		"text_simple": " out of mana ",
		"criteria": "NoMana Isdazzle MediumNag",
		"pretty_criteria": "Not enough mana (medium naggy)"
	},
	{
		"name": "dazz_nomana_05",
		"fullname": "dazzle_dazz_nomana_05",
		"mp3": "/sounds/vo/dazzle/dazz_nomana_05.mp3",
		"hero_id": 50,
		"voice_id": 50,
		"text": "No mana.",
		"text_simple": " no mana ",
		"criteria": "NoMana Isdazzle MediumNag",
		"pretty_criteria": "Not enough mana (medium naggy)"
	},
	{
		"name": "dazz_nomana_06",
		"fullname": "dazzle_dazz_nomana_06",
		"mp3": "/sounds/vo/dazzle/dazz_nomana_06.mp3",
		"hero_id": 50,
		"voice_id": 50,
		"text": "Not enough mana.",
		"text_simple": " not enough mana ",
		"criteria": "NoMana Isdazzle MediumNag",
		"pretty_criteria": "Not enough mana (medium naggy)"
	},
	{
		"name": "dazz_nomana_07",
		"fullname": "dazzle_dazz_nomana_07",
		"mp3": "/sounds/vo/dazzle/dazz_nomana_07.mp3",
		"hero_id": 50,
		"voice_id": 50,
		"text": "Out of mana.",
		"text_simple": " out of mana ",
		"criteria": "NoMana Isdazzle SuperNag",
		"pretty_criteria": "Not enough mana (very naggy)"
	},
	{
		"name": "dazz_nomana_08",
		"fullname": "dazzle_dazz_nomana_08",
		"mp3": "/sounds/vo/dazzle/dazz_nomana_08.mp3",
		"hero_id": 50,
		"voice_id": 50,
		"text": "No mana.",
		"text_simple": " no mana ",
		"criteria": "NoMana Isdazzle SuperNag",
		"pretty_criteria": "Not enough mana (very naggy)"
	},
	{
		"name": "dazz_nomana_09",
		"fullname": "dazzle_dazz_nomana_09",
		"mp3": "/sounds/vo/dazzle/dazz_nomana_09.mp3",
		"hero_id": 50,
		"voice_id": 50,
		"text": "Not enough mana.",
		"text_simple": " not enough mana ",
		"criteria": "NoMana Isdazzle SuperNag",
		"pretty_criteria": "Not enough mana (very naggy)"
	},
	{
		"name": "dazz_lose_01",
		"fullname": "dazzle_dazz_lose_01",
		"mp3": "/sounds/vo/dazzle/dazz_lose_01.mp3",
		"hero_id": 50,
		"voice_id": 50,
		"text": "No!",
		"text_simple": " no ",
		"criteria": "Defeat Isdazzle",
		"pretty_criteria": "Losing a game"
	},
	{
		"name": "dazz_lose_02",
		"fullname": "dazzle_dazz_lose_02",
		"mp3": "/sounds/vo/dazzle/dazz_lose_02.mp3",
		"hero_id": 50,
		"voice_id": 50,
		"text": "Defeated!",
		"text_simple": " defeated ",
		"criteria": "Defeat Isdazzle",
		"pretty_criteria": "Losing a game"
	},
	{
		"name": "dazz_lose_03",
		"fullname": "dazzle_dazz_lose_03",
		"mp3": "/sounds/vo/dazzle/dazz_lose_03.mp3",
		"hero_id": 50,
		"voice_id": 50,
		"text": "The order will have my shadow for this!",
		"text_simple": " the order will have my shadow for this ",
		"criteria": "Defeat Isdazzle",
		"pretty_criteria": "Losing a game"
	},
	{
		"name": "dazz_win_01",
		"fullname": "dazzle_dazz_win_01",
		"mp3": "/sounds/vo/dazzle/dazz_win_01.mp3",
		"hero_id": 50,
		"voice_id": 50,
		"text": "Yes!",
		"text_simple": " yes ",
		"criteria": "Victory Isdazzle",
		"pretty_criteria": "Winning a game"
	},
	{
		"name": "dazz_win_02",
		"fullname": "dazzle_dazz_win_02",
		"mp3": "/sounds/vo/dazzle/dazz_win_02.mp3",
		"hero_id": 50,
		"voice_id": 50,
		"text": "Victory!",
		"text_simple": " victory ",
		"criteria": "Victory Isdazzle",
		"pretty_criteria": "Winning a game"
	},
	{
		"name": "dazz_win_03",
		"fullname": "dazzle_dazz_win_03",
		"mp3": "/sounds/vo/dazzle/dazz_win_03.mp3",
		"hero_id": 50,
		"voice_id": 50,
		"text": "My shadow shall darken all creation.",
		"text_simple": " my shadow shall darken all creation ",
		"criteria": "Custom Isdazzle IsDazzleLoadoutSpawn|Victory Isdazzle",
		"pretty_criteria": "Spawning in the loadout|Winning a game"
	},
	{
		"name": "dazz_pain_01",
		"fullname": "dazzle_dazz_pain_01",
		"mp3": "/sounds/vo/dazzle/dazz_pain_01.mp3",
		"hero_id": 50,
		"voice_id": 50,
		"text": "Uh!",
		"text_simple": " uh ",
		"criteria": "Pain Isdazzle",
		"pretty_criteria": "Taking damage"
	},
	{
		"name": "dazz_pain_02",
		"fullname": "dazzle_dazz_pain_02",
		"mp3": "/sounds/vo/dazzle/dazz_pain_02.mp3",
		"hero_id": 50,
		"voice_id": 50,
		"text": "Ow!",
		"text_simple": " ow ",
		"criteria": "Pain Isdazzle",
		"pretty_criteria": "Taking damage"
	},
	{
		"name": "dazz_pain_03",
		"fullname": "dazzle_dazz_pain_03",
		"mp3": "/sounds/vo/dazzle/dazz_pain_03.mp3",
		"hero_id": 50,
		"voice_id": 50,
		"text": "Ooh!",
		"text_simple": " ooh ",
		"criteria": "Pain Isdazzle",
		"pretty_criteria": "Taking damage"
	},
	{
		"name": "dazz_pain_04",
		"fullname": "dazzle_dazz_pain_04",
		"mp3": "/sounds/vo/dazzle/dazz_pain_04.mp3",
		"hero_id": 50,
		"voice_id": 50,
		"text": "Oowa ah!",
		"text_simple": " oowa ah ",
		"pretty_criteria": "Unused"
	},
	{
		"name": "dazz_pain_05",
		"fullname": "dazzle_dazz_pain_05",
		"mp3": "/sounds/vo/dazzle/dazz_pain_05.mp3",
		"hero_id": 50,
		"voice_id": 50,
		"text": "Ah!",
		"text_simple": " ah ",
		"criteria": "Pain Isdazzle",
		"pretty_criteria": "Taking damage"
	},
	{
		"name": "dazz_pain_06",
		"fullname": "dazzle_dazz_pain_06",
		"mp3": "/sounds/vo/dazzle/dazz_pain_06.mp3",
		"hero_id": 50,
		"voice_id": 50,
		"text": "Ah!",
		"text_simple": " ah ",
		"criteria": "Pain Isdazzle",
		"pretty_criteria": "Taking damage"
	},
	{
		"name": "dazz_pain_07",
		"fullname": "dazzle_dazz_pain_07",
		"mp3": "/sounds/vo/dazzle/dazz_pain_07.mp3",
		"hero_id": 50,
		"voice_id": 50,
		"text": "Eh!",
		"text_simple": " eh ",
		"criteria": "Pain Isdazzle",
		"pretty_criteria": "Taking damage"
	},
	{
		"name": "dazz_pain_08",
		"fullname": "dazzle_dazz_pain_08",
		"mp3": "/sounds/vo/dazzle/dazz_pain_08.mp3",
		"hero_id": 50,
		"voice_id": 50,
		"text": "Hwat!",
		"text_simple": " hwat ",
		"criteria": "Pain Isdazzle",
		"pretty_criteria": "Taking damage"
	},
	{
		"name": "dazz_pain_09",
		"fullname": "dazzle_dazz_pain_09",
		"mp3": "/sounds/vo/dazzle/dazz_pain_09.mp3",
		"hero_id": 50,
		"voice_id": 50,
		"text": "Tah!",
		"text_simple": " tah ",
		"criteria": "Pain Isdazzle",
		"pretty_criteria": "Taking damage"
	},
	{
		"name": "dazz_pain_10",
		"fullname": "dazzle_dazz_pain_10",
		"mp3": "/sounds/vo/dazzle/dazz_pain_10.mp3",
		"hero_id": 50,
		"voice_id": 50,
		"text": "Ko-ah!",
		"text_simple": " koah ",
		"pretty_criteria": "Unused"
	},
	{
		"name": "dazz_pain_11",
		"fullname": "dazzle_dazz_pain_11",
		"mp3": "/sounds/vo/dazzle/dazz_pain_11.mp3",
		"hero_id": 50,
		"voice_id": 50,
		"text": "Kah!",
		"text_simple": " kah ",
		"criteria": "Pain Isdazzle",
		"pretty_criteria": "Taking damage"
	},
	{
		"name": "dazz_pain_12",
		"fullname": "dazzle_dazz_pain_12",
		"mp3": "/sounds/vo/dazzle/dazz_pain_12.mp3",
		"hero_id": 50,
		"voice_id": 50,
		"text": "Uh ah!",
		"text_simple": " uh ah ",
		"criteria": "Pain Isdazzle",
		"pretty_criteria": "Taking damage"
	},
	{
		"name": "dazz_anger_01",
		"fullname": "dazzle_dazz_anger_01",
		"mp3": "/sounds/vo/dazzle/dazz_anger_01.mp3",
		"hero_id": 50,
		"voice_id": 50,
		"text": "Numm.",
		"text_simple": " numm ",
		"pretty_criteria": "Unused"
	},
	{
		"name": "dazz_anger_02",
		"fullname": "dazzle_dazz_anger_02",
		"mp3": "/sounds/vo/dazzle/dazz_anger_02.mp3",
		"hero_id": 50,
		"voice_id": 50,
		"text": "Urrruh.",
		"text_simple": " urrruh ",
		"pretty_criteria": "Unused"
	},
	{
		"name": "dazz_anger_03",
		"fullname": "dazzle_dazz_anger_03",
		"mp3": "/sounds/vo/dazzle/dazz_anger_03.mp3",
		"hero_id": 50,
		"voice_id": 50,
		"text": "Hrrrrr.",
		"text_simple": " hrrrrr ",
		"pretty_criteria": "Unused"
	},
	{
		"name": "dazz_anger_04",
		"fullname": "dazzle_dazz_anger_04",
		"mp3": "/sounds/vo/dazzle/dazz_anger_04.mp3",
		"hero_id": 50,
		"voice_id": 50,
		"text": "Mrruuf.",
		"text_simple": " mrruuf ",
		"pretty_criteria": "Unused"
	},
	{
		"name": "dazz_anger_05",
		"fullname": "dazzle_dazz_anger_05",
		"mp3": "/sounds/vo/dazzle/dazz_anger_05.mp3",
		"hero_id": 50,
		"voice_id": 50,
		"text": "Grrr.",
		"text_simple": " grrr ",
		"pretty_criteria": "Unused"
	},
	{
		"name": "dazz_anger_06",
		"fullname": "dazzle_dazz_anger_06",
		"mp3": "/sounds/vo/dazzle/dazz_anger_06.mp3",
		"hero_id": 50,
		"voice_id": 50,
		"text": "Hrruf.",
		"text_simple": " hrruf ",
		"pretty_criteria": "Unused"
	},
	{
		"name": "dazz_happy_01",
		"fullname": "dazzle_dazz_happy_01",
		"mp3": "/sounds/vo/dazzle/dazz_happy_01.mp3",
		"hero_id": 50,
		"voice_id": 50,
		"text": "Ahhh.",
		"text_simple": " ahhh ",
		"pretty_criteria": "Unused"
	},
	{
		"name": "dazz_happy_02",
		"fullname": "dazzle_dazz_happy_02",
		"mp3": "/sounds/vo/dazzle/dazz_happy_02.mp3",
		"hero_id": 50,
		"voice_id": 50,
		"text": "Ahhh.",
		"text_simple": " ahhh ",
		"pretty_criteria": "Unused"
	},
	{
		"name": "dazz_happy_03",
		"fullname": "dazzle_dazz_happy_03",
		"mp3": "/sounds/vo/dazzle/dazz_happy_03.mp3",
		"hero_id": 50,
		"voice_id": 50,
		"text": "Haa.",
		"text_simple": " haa ",
		"criteria": "ItemDrop Isdazzle IsCommonDrop",
		"pretty_criteria": "Recieving a common cosmetic item"
	},
	{
		"name": "dazz_laugh_01",
		"fullname": "dazzle_dazz_laugh_01",
		"mp3": "/sounds/vo/dazzle/dazz_laugh_01.mp3",
		"hero_id": 50,
		"voice_id": 50,
		"text": "Uh ha ha ha ha ho!",
		"text_simple": " uh ha ha ha ha ho ",
		"criteria": "Kill Isdazzle|Emote Isdazzle IsEmoteLaugh",
		"pretty_criteria": "Killing a hero|Laughing"
	},
	{
		"name": "dazz_laugh_02",
		"fullname": "dazzle_dazz_laugh_02",
		"mp3": "/sounds/vo/dazzle/dazz_laugh_02.mp3",
		"hero_id": 50,
		"voice_id": 50,
		"text": "Ha ha har ha ha ha!",
		"text_simple": " ha ha har ha ha ha ",
		"criteria": "ItemDrop Isdazzle IsRareDrop|Emote Isdazzle IsEmoteLaugh|HeroChatWheel BronzeTier",
		"pretty_criteria": "Recieving a rare cosmetic item|Laughing|A bronze hero chat wheel was used"
	},
	{
		"name": "dazz_laugh_03",
		"fullname": "dazzle_dazz_laugh_03",
		"mp3": "/sounds/vo/dazzle/dazz_laugh_03.mp3",
		"hero_id": 50,
		"voice_id": 50,
		"text": "He he he he he he he!",
		"text_simple": " he he he he he he he ",
		"criteria": "Emote Isdazzle IsEmoteLaugh",
		"pretty_criteria": "Laughing"
	},
	{
		"name": "dazz_laugh_04",
		"fullname": "dazzle_dazz_laugh_04",
		"mp3": "/sounds/vo/dazzle/dazz_laugh_04.mp3",
		"hero_id": 50,
		"voice_id": 50,
		"text": "He he he he he he he he he!",
		"text_simple": " he he he he he he he he he ",
		"criteria": "Emote Isdazzle IsEmoteLaugh",
		"pretty_criteria": "Laughing"
	},
	{
		"name": "dazz_laugh_05",
		"fullname": "dazzle_dazz_laugh_05",
		"mp3": "/sounds/vo/dazzle/dazz_laugh_05.mp3",
		"hero_id": 50,
		"voice_id": 50,
		"text": "Ho ho ho ho yeah.",
		"text_simple": " ho ho ho ho yeah ",
		"criteria": "ItemDrop Isdazzle IsUltraRareDrop|Emote Isdazzle IsEmoteLaugh",
		"pretty_criteria": "Recieving an ultra rare cosmetic item|Laughing"
	},
	{
		"name": "dazz_laugh_06",
		"fullname": "dazzle_dazz_laugh_06",
		"mp3": "/sounds/vo/dazzle/dazz_laugh_06.mp3",
		"hero_id": 50,
		"voice_id": 50,
		"text": "Ho ho ha ha ha ha.",
		"text_simple": " ho ho ha ha ha ha ",
		"criteria": "Kill Isdazzle|Emote Isdazzle IsEmoteLaugh",
		"pretty_criteria": "Killing a hero|Laughing"
	},
	{
		"name": "dazz_laugh_07",
		"fullname": "dazzle_dazz_laugh_07",
		"mp3": "/sounds/vo/dazzle/dazz_laugh_07.mp3",
		"hero_id": 50,
		"voice_id": 50,
		"text": "Uh he he he he ha!",
		"text_simple": " uh he he he he ha ",
		"criteria": "Kill Isdazzle|Emote Isdazzle IsEmoteLaugh",
		"pretty_criteria": "Killing a hero|Laughing"
	},
	{
		"name": "dazz_laugh_08",
		"fullname": "dazzle_dazz_laugh_08",
		"mp3": "/sounds/vo/dazzle/dazz_laugh_08.mp3",
		"hero_id": 50,
		"voice_id": 50,
		"text": "Uh huh ha ha ha!",
		"text_simple": " uh huh ha ha ha ",
		"criteria": "Kill Isdazzle|Emote Isdazzle IsEmoteLaugh",
		"pretty_criteria": "Killing a hero|Laughing"
	},
	{
		"name": "dazz_laugh_09",
		"fullname": "dazzle_dazz_laugh_09",
		"mp3": "/sounds/vo/dazzle/dazz_laugh_09.mp3",
		"hero_id": 50,
		"voice_id": 50,
		"text": "Ha ha ha ha ha!",
		"text_simple": " ha ha ha ha ha ",
		"criteria": "Kill Isdazzle|Emote Isdazzle IsEmoteLaugh",
		"pretty_criteria": "Killing a hero|Laughing"
	}
]